graph_tools/__init__.py
graph_tools-1.14.data/scripts/graphfilt
graph_tools-1.14.data/scripts/graphgen
graph_tools-1.14.data/scripts/graphstat
graph_tools-1.14.dist-info/LICENSE
graph_tools-1.14.dist-info/METADATA
graph_tools-1.14.dist-info/WHEEL
graph_tools-1.14.dist-info/top_level.txt
graph_tools-1.14.dist-info/RECORD
