Metadata-Version: 2.1
Name: graph-tools
Version: 1.14
Summary: tools for graph theory and network science with many generation models
Home-page: https://github.com/h-ohsaki/graph-tools
Author: Hiroyuki Ohsaki
Author-email: ohsaki@lsnl.jp
Classifier: Programming Language :: Python :: 3
Classifier: License :: OSI Approved :: GNU General Public License v3 (GPLv3)
Classifier: Operating System :: OS Independent
License-File: LICENSE
Requires-Dist: numpy
Requires-Dist: perlcompat
Requires-Dist: pytess
Requires-Dist: tbdump
